hk1980/__init__.py
hk1980/core.py
hk1980/transformer.py
hk1980-0.2.3.dist-info/LICENSE
hk1980-0.2.3.dist-info/METADATA
hk1980-0.2.3.dist-info/WHEEL
hk1980-0.2.3.dist-info/RECORD
