Metadata-Version: 2.3
Name: hk1980
Version: 0.2.3
Summary: A forked project from hk80. This project also convert the coordinates between Hong Kong 1980 Grid System and World Geodetic System 1984 with pyproj, with a more update version of pyproj and providing better performance.
License: MIT
Keywords: hk80,hk1980,wgs1984,wgs84,grid,coordinate,hk
Author: Kavan Chan
Author-email: kavandevelopment@gmail.com
Requires-Python: >=3.10,<4.0
Classifier: License :: OSI Approved :: MIT License
Classifier: Programming Language :: Python :: 3
Classifier: Programming Language :: Python :: 3.10
Classifier: Programming Language :: Python :: 3.11
Classifier: Programming Language :: Python :: 3.12
Classifier: Programming Language :: Python :: 3.13
Requires-Dist: pyproj (>=3.5.0,<4.0.0)
Project-URL: Homepage, https://github.com/kavandev/hk1980
Project-URL: Repository, https://github.com/kavandev/hk1980
